{
  "CgmExpc": {
    "resultMsg": "success",
    "키워드": "산업안전",
    "page": "1",
    "resultCode": "00",
    "target": "moelCgmExpc",
    "totalCnt": "998",
    "cgmExpc": [
      {
        "id": "1",
        "안건명": "06.1.1 이후 채용시 건강진단 비용의 산업안전보건관리비 사용가능 여부",
        "해석기관코드": "1492000",
        "법령해석상세링크": "/DRF/lawService.do?OC=xognl427&target=moelCgmExpc&ID=28212&type=HTML&mobileYn=",
        "안건번호": "산업안전팀-1961",
        "법령해석일련번호": "28212",
        "질의기관명": "",
        "해석기관명": "고용노동부",
        "해석일자": "2005.12.28",
        "질의기관코드": "",
        "데이터기준일시": "2024.12.16"
      },
      {
        "id": "2",
        "안건명": "100억원 이상 하도급 계약 안전관리자 선임",
        "해석기관코드": "1492000",
        "법령해석상세링크": "/DRF/lawService.do?OC=xognl427&target=moelCgmExpc&ID=30332&type=HTML&mobileYn=",
        "안건번호": "산업안전과-5978",
        "법령해석일련번호": "30332",
        "질의기관명": "",
        "해석기관명": "고용노동부",
        "해석일자": "2020.12.28",
        "질의기관코드": "",
        "데이터기준일시": "2024.12.16"
      },
      {
        "id": "3",
        "안건명": "154KV관련 공사의 공사종류 등에 대한 회시",
        "해석기관코드": "1492000",
        "법령해석상세링크": "/DRF/lawService.do?OC=xognl427&target=moelCgmExpc&ID=27714&type=HTML&mobileYn=",
        "안건번호": "산업안전팀-2687",
        "법령해석일련번호": "27714",
        "질의기관명": "",
        "해석기관명": "고용노동부",
        "해석일자": "2007.05.29",
        "질의기관코드": "",
        "데이터기준일시": "2024.12.16"
      },
      {
        "id": "4",
        "안건명": "1개 병원은 노동조합의 대표자가 근로자대표로, 1개 병원은 자체 선출된 사람이 각각 산업안전보건위원회 근로자 대표로 되어 있을 경우 노동조합 대표자가 다른 사업장의 근로자위원 교체를 요구할 수 있는지 여부 등",
        "해석기관코드": "1492000",
        "법령해석상세링크": "/DRF/lawService.do?OC=xognl427&target=moelCgmExpc&ID=29096&type=HTML&mobileYn=",
        "안건번호": "산재예방정책과-331",
        "법령해석일련번호": "29096",
        "질의기관명": "",
        "해석기관명": "고용노동부",
        "해석일자": "2012.01.18",
        "질의기관코드": "",
        "데이터기준일시": "2024.12.16"
      },
      {
        "id": "5",
        "안건명": "2020.1. 16. 시행이전 산업안전보건법 제28조 유해작업 도급금지 조항에 대하여",
        "해석기관코드": "1492000",
        "법령해석상세링크": "/DRF/lawService.do?OC=xognl427&target=moelCgmExpc&ID=2287777&type=HTML&mobileYn=",
        "안건번호": "",
        "법령해석일련번호": "2287777",
        "질의기관명": "",
        "해석기관명": "고용노동부",
        "해석일자": "2025.07.07",
        "질의기관코드": "",
        "데이터기준일시": "2025.12.11"
      }
    ],
    "section": "itmNm",
    "numOfRows": "5"
  }
}